multi_logger-0.1.dist-info/DESCRIPTION.rst
multi_logger-0.1.dist-info/METADATA
multi_logger-0.1.dist-info/RECORD
multi_logger-0.1.dist-info/WHEEL
multi_logger-0.1.dist-info/metadata.json
multi_logger-0.1.dist-info/top_level.txt
multilogger/__init__.py
