Metadata-Version: 2.0
Name: multi-logger
Version: 0.1
Summary: Multi channel configurable logger
Home-page: https://github.com/ahmedrshdy/multi-logger
Author: Ahmed Roshdy
Author-email: a.elshalaby@e-tawasol.com
License: proprietary
Platform: UNKNOWN
Classifier: Development Status :: 4 - Beta
Classifier: Intended Audience :: Developers
Classifier: License :: OSI Approved :: GNU Lesser General Public License v3 (LGPLv3)
Classifier: Programming Language :: Python :: 3
Requires-Dist: watchtower (>=0.4.1)
Requires-Dist: boto3 (>=1.4.7)
